CONTRIBUTING.md
LICENSE
MANIFEST.in
README.rst
bale
setup.py
baler/__init__.py
baler/baler.py
baler.egg-info/PKG-INFO
baler.egg-info/SOURCES.txt
baler.egg-info/dependency_links.txt
baler.egg-info/requires.txt
baler.egg-info/top_level.txt
baler/templates/BalerBundle.h.j2
baler/templates/BalerBundle.m.j2