Metadata-Version: 1.0
Name: baler
Version: 1.0.2
Summary: Bundle assets into iOS static libraries
Home-page: https://github.com/paypal/baler
Author: PayPal SDK Team
Author-email: brfitzgerald@paypal.com, jbleechersnyder@paypal.com
License: The MIT License (MIT)
